dorothy/__init__.py
dorothy/__main__.py
dorothy/config.py
dorothy/core.py
dorothy/main.py
dorothy/wrappers.py
dorothy/etc/__init__.py
dorothy/etc/logging_config_template.yaml
dorothy/modules/__init__.py
dorothy/modules/manage_config.py
dorothy/modules/defense_evasion/__init__.py
dorothy/modules/defense_evasion/change_app_state.py
dorothy/modules/defense_evasion/change_policy_state.py
dorothy/modules/defense_evasion/change_rule_state.py
dorothy/modules/defense_evasion/change_zone_state.py
dorothy/modules/defense_evasion/defense_evasion.py
dorothy/modules/defense_evasion/modify_policy.py
dorothy/modules/defense_evasion/modify_policy_rule.py
dorothy/modules/defense_evasion/modify_zone.py
dorothy/modules/discovery/__init__.py
dorothy/modules/discovery/discovery.py
dorothy/modules/discovery/find_admin_groups.py
dorothy/modules/discovery/find_admins.py
dorothy/modules/discovery/find_users_without_mfa.py
dorothy/modules/discovery/get_apps.py
dorothy/modules/discovery/get_groups.py
dorothy/modules/discovery/get_policies.py
dorothy/modules/discovery/get_policy.py
dorothy/modules/discovery/get_user.py
dorothy/modules/discovery/get_users.py
dorothy/modules/discovery/get_zones.py
dorothy/modules/impact/__init__.py
dorothy/modules/impact/impact.py
dorothy/modules/persistence/__init__.py
dorothy/modules/persistence/change_user_state.py
dorothy/modules/persistence/create_admin_group.py
dorothy/modules/persistence/create_admin_user.py
dorothy/modules/persistence/create_user.py
dorothy/modules/persistence/delete_factor.py
dorothy/modules/persistence/persistence.py
dorothy/modules/persistence/reset_factors.py
dorothy/modules/persistence/reset_password.py
dorothy/modules/persistence/set_recovery_question.py
dorothy-0.2.1.dist-info/LICENSE.txt
dorothy-0.2.1.dist-info/METADATA
dorothy-0.2.1.dist-info/NOTICE.txt
dorothy-0.2.1.dist-info/WHEEL
dorothy-0.2.1.dist-info/entry_points.txt
dorothy-0.2.1.dist-info/top_level.txt
dorothy-0.2.1.dist-info/RECORD
