Metadata-Version: 2.1
Name: dorothy
Version: 0.2.1
Summary: Dorothy is a tool to test security monitoring and detection for Okta environments
Home-page: https://github.com/elastic/dorothy
Author: David French
Author-email: threatpunter@gmail.com
Maintainer: Elastic
License: Apache License 2.0
Platform: UNKNOWN
Classifier: Intended Audience :: Information Technology
Classifier: Intended Audience :: System Administrators
Classifier: License :: OSI Approved :: Apache Software License
Classifier: Operating System :: OS Independent
Classifier: Programming Language :: Python :: 3
Classifier: Programming Language :: Python :: 3.7
Classifier: Programming Language :: Python :: 3.8
Classifier: Topic :: Security
Requires-Dist: PyYAML (~=5.3.1)
Requires-Dist: click (~=7.1.2)
Requires-Dist: requests (~=2.24.0)
Requires-Dist: tabulate (~=0.8.7)
Requires-Dist: setuptools (~=50.3.2)
Requires-Dist: click-shell (~=2.0)
Requires-Dist: elasticsearch (~=7.10.0)
Requires-Dist: colorama (~=0.4.4) ; platform_system == "Windows"
Requires-Dist: pyreadline (==2.1) ; platform_system == "Windows"
